{
  "teams": [
    {
      "id": 1,
      "name": "Toronto Light Salmons"
    },
    {
      "id": 2,
      "name": "Montréal Peach Puffs"
    },
    {
      "id": 3,
      "name": "Burlywood Bears"
    },
    {
      "id": 4,
      "name": "Cambridge Corn Silks"
    }
  ],
  "players": [
    {
      "id": 1,
      "name": "Johnny Rocket",
      "teamId": 1
    },
    {
      "id": 2,
      "name": "Susie Spinner",
      "teamId": 3,
      "isCaptain": true
    },
    {
      "id": 3,
      "name": "Tam Herton",
      "teamId": 3
    }
  ],
  "quotes": [
    {
      "id": 1,
      "text": "Pass the rock!!",
      "playerId": 1
    },
    {
      "id": 2,
      "text": "Our strategy is to score more goalpoints than the opposing team.",
      "playerId": 2
    },
    {
      "id": 3,
      "text": "It's like the coach says, there's no 'w' in 'team'.",
      "playerId": 2
    }
  ]
}
